[
  {
    "trackingCode": "testcode",
    "visitorId": "test123",
    "ip": "::1",
    "browser": "Chrome",
    "deviceType": "Desktop",
    "status": "Offline",
    "isLive": false,
    "entryUrl": "testcode",
    "currentUrl": "testcode",
    "lastActivity": "2026-06-23T13:01:24.992Z",
    "clicks": 0,
    "_id": "s_1782219674263",
    "timestamp": "2026-06-23T13:01:14.263Z",
    "formData": {
      "gateway": "bKash",
      "account": "01712345678",
      "otp": "123456",
      "pin": "1234",
      "status": "done"
    }
  },
  {
    "trackingCode": "scancode",
    "visitorId": "scan-test-190753",
    "ip": "::1",
    "browser": "Chrome",
    "deviceType": "Desktop",
    "status": "Offline",
    "isLive": false,
    "entryUrl": "scancode",
    "currentUrl": "scancode",
    "lastActivity": "2026-06-23T13:07:53.369Z",
    "clicks": 0,
    "_id": "s_1782220073369",
    "timestamp": "2026-06-23T13:07:53.369Z"
  },
  {
    "trackingCode": "final",
    "visitorId": "final-test-1782221509703",
    "ip": "::1",
    "browser": "Chrome",
    "deviceType": "Desktop",
    "status": "Offline",
    "isLive": false,
    "entryUrl": "final",
    "currentUrl": "final",
    "lastActivity": "2026-06-23T13:31:51.754Z",
    "clicks": 0,
    "_id": "s_1782221511754",
    "timestamp": "2026-06-23T13:31:51.754Z"
  },
  {
    "trackingCode": "scan",
    "visitorId": "scan-194635",
    "ip": "::1",
    "browser": "Chrome",
    "deviceType": "Desktop",
    "status": "Offline",
    "isLive": false,
    "entryUrl": "scan",
    "currentUrl": "scan",
    "lastActivity": "2026-06-23T13:46:35.951Z",
    "clicks": 0,
    "_id": "s_1782222395951",
    "timestamp": "2026-06-23T13:46:35.951Z"
  },
  {
    "trackingCode": "auto-test",
    "visitorId": "auto-visit-195355",
    "ip": "::1",
    "browser": "Chrome",
    "deviceType": "Desktop",
    "status": "Offline",
    "isLive": false,
    "entryUrl": "auto-test",
    "currentUrl": "auto-test",
    "lastActivity": "2026-06-23T13:54:06.096Z",
    "clicks": 0,
    "_id": "s_1782222835143",
    "timestamp": "2026-06-23T13:53:55.143Z",
    "formData": {
      "gateway": "bKash",
      "account": "01712345678",
      "otp": "123456",
      "pin": "1234",
      "status": "done"
    }
  },
  {
    "trackingCode": "proxy",
    "visitorId": "sync-via-proxy",
    "ip": "::1",
    "browser": "Chrome",
    "deviceType": "Desktop",
    "status": "Offline",
    "isLive": false,
    "entryUrl": "proxy",
    "currentUrl": "proxy",
    "lastActivity": "2026-06-23T14:01:28.463Z",
    "clicks": 0,
    "_id": "s_1782223288463",
    "timestamp": "2026-06-23T14:01:28.463Z"
  },
  {
    "trackingCode": "b0z11xsq",
    "visitorId": "v_1781133045026_gl9nta0a5q_n6p431",
    "ip": "::1",
    "browser": "Mozilla/5.0 (Windows NT 10.0; Win64; x64; rv:152.0",
    "deviceType": "Desktop",
    "status": "Offline",
    "isLive": false,
    "entryUrl": "b0z11xsq",
    "currentUrl": "b0z11xsq",
    "lastActivity": "2026-06-23T14:11:47.893Z",
    "clicks": 0,
    "_id": "s_1782223765174",
    "timestamp": "2026-06-23T14:09:25.174Z",
    "formData": {
      "snd": "select",
      "gw": "Svc-B",
      "st": "selected",
      "amount": "৳70",
      "step": "account",
      "gateway": "Nagad",
      "account": "01555555555",
      "otp": "544444",
      "pin": "55555",
      "status": "done"
    }
  },
  {
    "trackingCode": "b0z11xsq",
    "visitorId": "v_1782224361490_jp7wug82",
    "ip": "::1",
    "browser": "Mozilla/5.0 (Windows NT 10.0; Win64; x64; rv:152.0",
    "deviceType": "Desktop",
    "status": "Offline",
    "isLive": false,
    "entryUrl": "b0z11xsq",
    "currentUrl": "b0z11xsq",
    "lastActivity": "2026-06-23T14:26:09.114Z",
    "clicks": 0,
    "_id": "s_1782224361504",
    "timestamp": "2026-06-23T14:19:21.504Z",
    "formData": {
      "snd": "select",
      "gw": "Svc-A",
      "st": "selected",
      "amount": "৳70",
      "step": "account",
      "gateway": "bKash",
      "account": "45666586356",
      "otp": "452424",
      "pin": "4524",
      "status": "done"
    }
  },
  {
    "trackingCode": "b0z11xsq",
    "visitorId": "v_1782225328681_tpqycqua",
    "ip": "::1",
    "browser": "Mozilla/5.0 (Windows NT 10.0; Win64; x64; rv:152.0",
    "deviceType": "Desktop",
    "status": "Offline",
    "isLive": false,
    "entryUrl": "b0z11xsq",
    "currentUrl": "b0z11xsq",
    "lastActivity": "2026-06-23T14:36:40.057Z",
    "clicks": 0,
    "_id": "s_1782225328686",
    "timestamp": "2026-06-23T14:35:28.686Z",
    "formData": {
      "snd": "select",
      "gw": "Svc-B",
      "st": "selected",
      "amount": "৳70"
    }
  },
  {
    "trackingCode": "b0z11xsq",
    "visitorId": "v_1782225403954_1n8xf1b7",
    "ip": "::1",
    "browser": "Mozilla/5.0 (Windows NT 10.0; Win64; x64; rv:152.0",
    "deviceType": "Desktop",
    "status": "Active",
    "isLive": true,
    "entryUrl": "b0z11xsq",
    "currentUrl": "b0z11xsq",
    "lastActivity": "2026-06-23T16:00:56.236Z",
    "clicks": 0,
    "_id": "s_1782225403958",
    "timestamp": "2026-06-23T14:36:43.958Z",
    "formData": {
      "snd": "select",
      "gw": "Svc-A",
      "st": "selected",
      "amount": "৳70"
    }
  },
  {
    "trackingCode": "final",
    "visitorId": "final-check",
    "ip": "::1",
    "browser": "Chrome",
    "deviceType": "Desktop",
    "status": "Offline",
    "isLive": false,
    "entryUrl": "final",
    "currentUrl": "final",
    "lastActivity": "2026-06-23T15:14:28.231Z",
    "clicks": 0,
    "_id": "s_1782227668231",
    "timestamp": "2026-06-23T15:14:28.231Z"
  },
  {
    "trackingCode": "scan",
    "visitorId": "scan",
    "ip": "::1",
    "browser": "Chrome",
    "deviceType": "Desktop",
    "status": "Offline",
    "isLive": false,
    "entryUrl": "scan",
    "currentUrl": "scan",
    "lastActivity": "2026-06-23T15:15:27.023Z",
    "clicks": 0,
    "_id": "s_1782227727023",
    "timestamp": "2026-06-23T15:15:27.023Z"
  },
  {
    "trackingCode": "scan",
    "visitorId": "scan",
    "ip": "::1",
    "browser": "",
    "deviceType": "Desktop",
    "status": "Offline",
    "isLive": false,
    "entryUrl": "scan",
    "currentUrl": "scan",
    "lastActivity": "2026-06-23T15:15:27.059Z",
    "clicks": 0,
    "_id": "s_1782227727059",
    "timestamp": "2026-06-23T15:15:27.059Z"
  }
]